secretsmanager/__init__.py
secretsmanager/secretsmanager.py
secretsmanager_nitro_dhaven-0.0.4.dist-info/LICENSE
secretsmanager_nitro_dhaven-0.0.4.dist-info/METADATA
secretsmanager_nitro_dhaven-0.0.4.dist-info/WHEEL
secretsmanager_nitro_dhaven-0.0.4.dist-info/top_level.txt
secretsmanager_nitro_dhaven-0.0.4.dist-info/RECORD
